README.md
setup.cfg
setup.py
userprint/__init__.py
userprint/userprint.py
userprint.egg-info/PKG-INFO
userprint.egg-info/SOURCES.txt
userprint.egg-info/dependency_links.txt
userprint.egg-info/top_level.txt