Metadata-Version: 2.1
Name: userprint
Version: 1.0.1
Summary: Python User Print Modules
Home-page: UNKNOWN
Author: Park Seung-Beom
Author-email: psbaio@gmail.com
License: 'MIT',
Keywords: print
Platform: UNKNOWN
Classifier: Development Status :: 2 - Pre-Alpha
